{"posts": {"data": [{"created_time": "2017-10-12T13:44:56+0000", "message": "En vivo #TodoLoDem\u00e1sTambi\u00e9n hoy sin Bebe Contepomi pero con Eleonora Perez Caressi, Martin Urruty, Ceci Baz\u00e1n, Violeta Santamarina y con el crack de Martin Pe\u00f1a que cumple a\u00f1os \ud83d\udcaa", "id": "51631931862_10154919423286863"}, {"created_time": "2017-10-12T13:02:02+0000", "message": "\ud83c\udf7a Lleg\u00f3 el d\u00eda del #Dec\u00edLaPosta al Bebe Contepomi en Mega 98.3. \u00a1Cargate de Cerveza Isenbeck para el fin de semana! \ud83c\udf7a", "id": "51631931862_10154919367401863"}, {"created_time": "2017-10-12T12:00:03+0000", "message": "A los nuevos sonidos de nuestro rock le vamos a dar el mejor sonido.\nFRI Movistar y Bebe Contepomi te presentan a las bandas que compiten por grabar en el m\u00edtico Abbey Road, el mejor estudio del mundo. Escuch\u00e1 #TodoLoDem\u00e1sTambi\u00e9n, vot\u00e1 a las bandas que m\u00e1s te gustan o\ninscrib\u00ed la tuya en FriMovistar.com.ar y viv\u00ed lo mejor del\nrock emergente. Movistar. Eleg\u00ed todo.", "id": "51631931862_10154919276251863"}, {"created_time": "2017-10-12T11:23:49+0000", "message": "El audio del que todos hablan del #ComentaristaChileno es nuestro Wat\u00f3n Rosenthal, ac\u00e1 el audio del los primeros minutos del partido #GolDeEcuador", "id": "51631931862_10154919233276863"}, {"created_time": "2017-10-12T11:23:30+0000", "message": "\ud83c\udfb6\ud83d\udcfbAHORA en #NoSeDesesperen estrenamos #Mancho el nuevo disco de Banda de Turistas #BandaDeTuristasEnMega\ud83d\udcfb\ud83c\udfb6", "id": "51631931862_10154919232971863"}, {"created_time": "2017-10-12T11:17:38+0000", "message": "El audio del que todos hablan del #ComentaristaChileno es nuestro Wat\u00f3n Rosenthal, ac\u00e1 el audio", "id": "51631931862_10154919226721863"}, {"created_time": "2017-10-12T08:11:03+0000", "message": "En #OilCombustibles nos orientamos a cada necesidad por eso contamos con un canal de distribuci\u00f3n orientado espec\u00edficamente a la actividad agropecuaria.", "story": "Mega 98.3 with Oil Combustibles.", "id": "51631931862_10154919047166863"}, {"created_time": "2017-10-12T02:25:01+0000", "message": "\u00bfTodav\u00eda no te enteraste? \u00a1En todas las estaciones de Oil Combustibles hay una nueva promo para vos! Ten\u00e9s que cargar $500 de nafta o di\u00e9sel, ingresar tu ticket en www.oilcombustibles.com y particip\u00e1s por una silla plegable. Es muy f\u00e1cil. \u00a1Ten\u00e9s tiempo hasta el 15 de octubre para pasar por tu estaci\u00f3n Oil m\u00e1s cercana! Consult\u00e1 los t\u00e9rminos y legales en www.veniaoilyllegamaslejos.com.ar", "story": "Mega 98.3 with Oil Combustibles.", "id": "51631931862_10154918620731863"}, {"created_time": "2017-10-12T02:03:01+0000", "message": "\ud83d\ude0e El 4 de noviembre llega la presentaci\u00f3n  de #Late, el nuevo disco de Jovenes Pordioseros Oficial y las entradas est\u00e1n en Mega 98.3. \u00bfVamos? \ud83c\udfb8", "story": "Mega 98.3 with Jovenes Pordioseros Oficial.", "id": "51631931862_10154918591461863"}, {"created_time": "2017-10-12T00:55:29+0000", "message": "Disfrutamos juntos #LaNocheDelRock \nYa est\u00e1 Christian Grosso para acompa\u00f1arte hasta las 2am! \nHoy #CortamosLaSemanaCon ?", "id": "51631931862_10154918475441863"}, {"created_time": "2017-10-12T00:42:02+0000", "message": "\ud83c\udfbc A 30 a\u00f1os del disco #SolosEnAm\u00e9rica, Miguel Mateos lo revisita en el Estadio Obras el 18 de noviembre y en Mega tenemos pases exclusivos para vos. Quedate escuchando la radio y consegu\u00ed tu lugar. \ud83c\udfbc", "story": "Mega 98.3 with Miguel Mateos.", "id": "51631931862_10154918452091863"}, {"created_time": "2017-10-11T23:34:59+0000", "message": "#Sab\u00edasQu\u00e9 \u2753\n\nMa\u00f1ana en No Se Desesperen, Martin Ciccioli y equipo van a presentar #Moncho, el nuevo \u00e1lbum de Banda de Turistas.\n\nY a partir de \u00e9ste viernes, el nuevo material de la banda se podr\u00e1 conseguir en formato f\u00edsico o a trav\u00e9s de las plataformas digitales.", "id": "51631931862_10154918295736863"}, {"created_time": "2017-10-11T22:17:26+0000", "message": "#TresAlHilo #EspecialBARock en Mega 98.3 \n\n1\u20e3 Dos d\u00edas en la vida - Fito Paez - P\u00e1gina oficial \u2705\n2\u20e3 No pibe - Manal \u2705\n3\u20e3 Odioso - La Mississippi\u2705", "id": "51631931862_10154918121251863"}, {"created_time": "2017-10-11T21:23:48+0000", "message": "\ud83c\udfb6 #NoticiasDelRockNacional \ud83c\udfb6\n\nDe La Gran Pi\u00f1ata con nueva fecha\n\nLuego de un a\u00f1o intenso, la banda tiene cita para cerrar el a\u00f1o el s\u00e1bado 11 de noviembre en Museum Live.\n\nPor otra parte, antes los podemos ver \u00e9ste lunes 16 de octubre en el d\u00eda tres del B.A.Rock", "id": "51631931862_10154918044331863"}, {"created_time": "2017-10-11T21:17:02+0000", "message": "\ud83c\udfb8 Nagual Rock llega a Obras por primera vez el 11 de noviembre y en Mega 98.3 tenemos un #Megapack con entradas + CD + remera. \u00a1Escuch\u00e1 la radio y ganalo! \ud83c\udfb8", "story": "Mega 98.3 with Nagual Rock.", "id": "51631931862_10154918034631863"}, {"created_time": "2017-10-11T21:13:50+0000", "message": "\ud83c\udfb6\ud83d\ude99#Peg\u00e1LaVuelta con Fran Mart\u00ednez Gonz\u00e1lez con informaci\u00f3n y #PuroRockNacional \ud83c\udfb6\ud83d\ude99", "id": "51631931862_10154918029541863"}, {"created_time": "2017-10-11T20:32:02+0000", "message": "Mega 98.3 te invita al Kustom Art, el octavo encuentro de la cultura Kustom de la Argentina. Ser\u00e1 el 18 y 19 de noviembre en el Centro Miguelete, en 25 de Mayo y General Paz. Kustom Art re\u00fane la pasi\u00f3n por el arte, el dise\u00f1o, los autos cl\u00e1sicos, las motos, la mejor gastronom\u00eda y mucho rock en vivo.", "story": "Mega 98.3 with Kustom Art.", "id": "51631931862_10154917956276863"}, {"created_time": "2017-10-11T19:43:01+0000", "message": "\ud83c\udfb6Escuch\u00e1 las pistas y decinos con qu\u00e9 cerramos el #Megadelivery . \nEl voucher de #LuzDeMar puede ser tuyo \ud83c\udfb6", "id": "51631931862_10154917872631863"}, {"created_time": "2017-10-11T18:17:03+0000", "message": "\ud83c\udfb6 #TresAlHilo de Las Pelotas en Mega 98.3 \ud83c\udfb6 \n\n1\u20e3 Ser\u00e1 \u2705\n2\u20e3 Revoluci\u00f3n\u2705\n3\u20e3 Si supieras\u2705", "id": "51631931862_10154917712891863"}, {"created_time": "2017-10-11T17:10:02+0000", "message": "\ud83c\udfbc El 30 de octubre Coti toca en el Teatro Col\u00f3n y en Mega 98.3 tenemos invitaciones para que lo veas en vivo. \u00bfQuer\u00e9s ir? \ud83c\udfbc", "story": "Mega 98.3 with Coti.", "id": "51631931862_10154917585411863"}, {"created_time": "2017-10-11T16:44:23+0000", "message": "\u2764\ufe0f\ud83c\udfb6Hoy estamos cari\u00f1osos en el #Megadelivery y queremos que suenen #MegaLentos Cari Deferrari \u2764\ufe0f\ud83c\udfb6", "id": "51631931862_10154917529961863"}, {"created_time": "2017-10-11T16:41:20+0000", "message": "\ud83c\udfb6\ud83d\udcfbB\u00e1rbara Mart\u00ednez ya tiene sus entradas que gan\u00f3 en #TodoLoDem\u00e1sTambi\u00e9n para ver \u00e9sta noche a Joystick en el estadio \u00danico de La Plata. Adem\u00e1s puede quedarse a ver a U2  \ud83d\udcfb\ud83c\udfb6", "id": "51631931862_10154917524331863"}, {"created_time": "2017-10-11T14:55:11+0000", "message": "Arranca el #ParqueTem\u00e1tico de #TodoLoDem\u00e1sTambi\u00e9n Hoy buscamos canciones para celebrar la calificaci\u00f3n de la Argentina \u00bfCu\u00e1l es la tuya? \u00bfPor qu\u00e9?", "id": "51631931862_10154917370411863"}, {"created_time": "2017-10-11T14:01:03+0000", "message": "\ud83c\udf7a And\u00e1 enfriando tu chopp que ma\u00f1ana llega #Dec\u00edLaPosta con Bebe Contepomi y pod\u00e9s ganarte Cerveza Isenbeck para disfrutar como quieras \ud83c\udf7a", "story": "Mega 98.3 with Cerveza Isenbeck.", "id": "51631931862_10154917286056863"}, {"created_time": "2017-10-11T13:26:58+0000", "message": "\ud83d\udcfb #TodoLoDem\u00e1sTambi\u00e9n en vivo con puro rock nacional de la mano de Bebe Contepomi, gran equipo y con Eleonora Perez Caressi despu\u00e9s de una noche larga \ud83d\udcaa", "id": "51631931862_10154917234201863"}, {"created_time": "2017-10-11T13:17:03+0000", "message": "\ud83c\udfb6\ud83d\udcfb De La Gran Pi\u00f1ata, despide el 2017 en #Museum, el s\u00e1bado 11 de noviembre y en Mega vamos a tener entradas para que no te lo pierdas\ud83d\udcfb\ud83c\udfb6", "id": "51631931862_10154917218621863"}, {"created_time": "2017-10-11T13:00:02+0000", "message": "Hoy se van las entradas para Joystick y...", "id": "51631931862_10154917197771863"}, {"created_time": "2017-10-11T12:07:05+0000", "message": "#ZetaEnMega", "story": "Mega 98.3 was live.", "id": "51631931862_10154917120771863"}, {"created_time": "2017-10-11T12:00:05+0000", "message": "A los nuevos sonidos de nuestro rock le vamos a dar el mejor sonido.\nFRI Movistar y Bebe Contepomi te presentan a las bandas que compiten por grabar en el m\u00edtico Abbey Road, el mejor estudio del mundo. Escuch\u00e1 #TodoLoDem\u00e1sTambi\u00e9n, vot\u00e1 a las bandas que m\u00e1s te gustan o\ninscrib\u00ed la tuya en FriMovistar.com.ar y viv\u00ed lo mejor del\nrock emergente. Movistar. Eleg\u00ed todo.", "id": "51631931862_10154917107141863"}, {"created_time": "2017-10-11T11:25:46+0000", "message": "Yo s\u00e9 que no siempre gana el que pega primero \ud83c\udfb6\ud83c\udfb6", "id": "51631931862_10154917068296863"}], "paging": {"cursors": {"before": "Q2c4U1pXNTBYM0YxWlhKNVgzTjBiM0o1WDJsa0R4NDFNVFl6TVRrek1UZAzJNam80TmpFek5USTVOelE1T0RNeE1URTVPVEVQREdGd2FWOXpkRzl5ZAVY5cFpBOGROVEUyTXpFNU16RTROakpmTVRBeE5UUTVNVGswTWpNeU9EWTROak1QQkhScGJXVUdXZADl4MkFFPQZDZD", "after": "Q2c4U1pXNTBYM0YxWlhKNVgzTjBiM0o1WDJsa0R4ODFNVFl6TVRrek1UZAzJNam94TVRBME5EWTFNVEkzTmpZAek1EQTFNekE0RHd4aGNHbGZAjM1J2Y25sZAmFXUVBIVFV4TmpNeE9UTXhPRFl5WHpFd01UVTBPVEUzTURZANE1qazJPRFl6RHdSMGFXMWxCbG5kLzdvQgZDZD"}, "next": "https://graph.facebook.com/v2.10/51631931862/posts?access_token=EAACEdEose0cBADBwEC0J0f6FNFpjturLq5SO7qsbZAoQ1LmMYo7xuCKfnABpgcK1xo5NQg4wVjDKfp2ztr5DRZBatvF7kSe1iPHoZArJMVayc5ZBydtC7ytzTqvvhImR2BCuZBHBo4E4fU66eZAjes61BtJ9m0FUxiP8rG4dtWqwCHy57h0mhbwZANABrWtf94ZD&pretty=1&limit=30&after=Q2c4U1pXNTBYM0YxWlhKNVgzTjBiM0o1WDJsa0R4ODFNVFl6TVRrek1UZAzJNam94TVRBME5EWTFNVEkzTmpZAek1EQTFNekE0RHd4aGNHbGZAjM1J2Y25sZAmFXUVBIVFV4TmpNeE9UTXhPRFl5WHpFd01UVTBPVEUzTURZANE1qazJPRFl6RHdSMGFXMWxCbG5kLzdvQgZDZD"}}, "id": "51631931862", "Source": "megafm983(4)"}